setup.py
vdt/__init__.py
vdt.versionplugin.puppetmodule.egg-info/PKG-INFO
vdt.versionplugin.puppetmodule.egg-info/SOURCES.txt
vdt.versionplugin.puppetmodule.egg-info/dependency_links.txt
vdt.versionplugin.puppetmodule.egg-info/namespace_packages.txt
vdt.versionplugin.puppetmodule.egg-info/requires.txt
vdt.versionplugin.puppetmodule.egg-info/top_level.txt
vdt.versionplugin.puppetmodule.egg-info/zip-safe
vdt/versionplugin/__init__.py
vdt/versionplugin/puppetmodule/__init__.py
vdt/versionplugin/puppetmodule/package.py
vdt/versionplugin/puppetmodule/shared.py