Metadata-Version: 1.0
Name: vdt.versionplugin.puppetmodule
Version: 0.1
Summary: Version Increment Plugin that builds a package from a puppet module
Home-page: UNKNOWN
Author: Lars van de Kerkhof
Author-email: lars@permanentmarkers.nl
License: UNKNOWN
Platform: UNKNOWN
